MANIFEST.in
README.md
requirements.txt
setup.cfg
setup.py
pykrundeck.egg-info/PKG-INFO
pykrundeck.egg-info/SOURCES.txt
pykrundeck.egg-info/dependency_links.txt
pykrundeck.egg-info/requires.txt
pykrundeck.egg-info/top_level.txt
pyrundeck/__init__.py
pyrundeck/rundeck.py