Metadata-Version: 1.0
Name: pykrundeck
Version: 0.92.1
Summary: Python REST API client for Rundeck 2.6+
Home-page: https://github.com/kalumkalac/pyrundeck
Author: kalumkalac
Author-email: delovan@gmail.com
License: UNKNOWN
Platform: UNKNOWN
